README.md
setup.py
floaty/__init__.py
floaty.egg-info/PKG-INFO
floaty.egg-info/SOURCES.txt
floaty.egg-info/dependency_links.txt
floaty.egg-info/top_level.txt