Metadata-Version: 2.1
Name: floaty
Version: 1.0.1
Summary: Bandages for boto3 floating-point wounds.
Home-page: https://github.com/tallesl/py-floaty
Author: Talles Lasmar
Author-email: talleslasmar@gmail.com
License: UNKNOWN
Platform: UNKNOWN
